noop_timer.py
noop_timer-0.0.1.dist-info/LICENSE
noop_timer-0.0.1.dist-info/METADATA
noop_timer-0.0.1.dist-info/WHEEL
noop_timer-0.0.1.dist-info/top_level.txt
noop_timer-0.0.1.dist-info/RECORD
