Metadata-Version: 2.1
Name: noop-timer
Version: 0.0.1
Summary: A package for calculating the time it takes to execute NOP bytecode operations
Home-page: https://github.com/pganssle/noop_timer
Author: Paul Ganssle
Author-email: paul@ganssle.io
License: UNKNOWN
Platform: UNKNOWN
Classifier: Development Status :: 3 - Alpha
Classifier: Intended Audience :: Developers
Classifier: License :: OSI Approved :: Apache Software License
Classifier: Programming Language :: Python :: 3.6
Classifier: Programming Language :: Python :: 3.7
Classifier: Topic :: Software Development :: Libraries
Requires-Python: >= 3.6
Requires-Dist: progressbar2
Requires-Dist: matplotlib
Requires-Dist: numpy
Requires-Dist: codetransformer
Requires-Dist: py-cpuinfo
